odoo/addons/hr_expense_invoice/README.rst
odoo/addons/hr_expense_invoice/__init__.py
odoo/addons/hr_expense_invoice/__manifest__.py
odoo/addons/hr_expense_invoice/data/mail_message_subtype.xml
odoo/addons/hr_expense_invoice/i18n/cs_CZ.po
odoo/addons/hr_expense_invoice/i18n/de.po
odoo/addons/hr_expense_invoice/i18n/es.po
odoo/addons/hr_expense_invoice/i18n/fr.po
odoo/addons/hr_expense_invoice/i18n/hr.po
odoo/addons/hr_expense_invoice/i18n/hr_expense_invoice.pot
odoo/addons/hr_expense_invoice/i18n/it.po
odoo/addons/hr_expense_invoice/i18n/nl_NL.po
odoo/addons/hr_expense_invoice/i18n/pt.po
odoo/addons/hr_expense_invoice/models/__init__.py
odoo/addons/hr_expense_invoice/models/account_move.py
odoo/addons/hr_expense_invoice/models/hr_expense.py
odoo/addons/hr_expense_invoice/models/hr_expense_sheet.py
odoo/addons/hr_expense_invoice/readme/CONTRIBUTORS.md
odoo/addons/hr_expense_invoice/readme/DESCRIPTION.md
odoo/addons/hr_expense_invoice/readme/ROADMAP.md
odoo/addons/hr_expense_invoice/readme/USAGE.md
odoo/addons/hr_expense_invoice/static/description/icon.png
odoo/addons/hr_expense_invoice/static/description/index.html
odoo/addons/hr_expense_invoice/tests/__init__.py
odoo/addons/hr_expense_invoice/tests/test_hr_expense_invoice.py
odoo/addons/hr_expense_invoice/views/account_move_views.xml
odoo/addons/hr_expense_invoice/views/hr_expense_views.xml
odoo_addon_hr_expense_invoice-18.0.1.0.2.dist-info/METADATA
odoo_addon_hr_expense_invoice-18.0.1.0.2.dist-info/WHEEL
odoo_addon_hr_expense_invoice-18.0.1.0.2.dist-info/top_level.txt
odoo_addon_hr_expense_invoice-18.0.1.0.2.dist-info/RECORD
